Workbook

Sheet Clients
A1: Emotion Box — Client Tracker
A2: Fill in one row per client. Columns marked with * have a dropdown — click the cell and choose from the list.
A4: Client Name | B4: Phone / WhatsApp | C4: Occasion * | D4: Event Date | E4: Location | F4: Package * | G4: Price (€) | H4: Deposit Paid (€) | I4: Balance Due (€) | J4: Gift Cost (€) | K4: Net Profit (€) | L4: Status * | M4: Gift Bought By * | N4: Notes
A5: Maria Georgiou | B5: +357 99 123 456 | C5: Birthday | D5: 2026-09-20 | E5: Limassol | F5: Gold | G5: 270 | H5: 100 | I5: =G5-H5 -> 170 | J5: 35 | K5: =G5-J5 -> 235 | L5: Confirmed | M5: Emotion Box | N5: Wants a violinist if possible
I6: =G6-H6 -> 0 | K6: =G6-J6 -> 0
I7: =G7-H7 -> 0 | K7: =G7-J7 -> 0
I8: =G8-H8 -> 0 | K8: =G8-J8 -> 0
I9: =G9-H9 -> 0 | K9: =G9-J9 -> 0
I10: =G10-H10 -> 0 | K10: =G10-J10 -> 0
I11: =G11-H11 -> 0 | K11: =G11-J11 -> 0
I12: =G12-H12 -> 0 | K12: =G12-J12 -> 0
I13: =G13-H13 -> 0 | K13: =G13-J13 -> 0
I14: =G14-H14 -> 0 | K14: =G14-J14 -> 0
I15: =G15-H15 -> 0 | K15: =G15-J15 -> 0
I16: =G16-H16 -> 0 | K16: =G16-J16 -> 0
I17: =G17-H17 -> 0 | K17: =G17-J17 -> 0
... I40: =G40-H40 -> 0 | K40: =G40-J40 -> 0

Sheet Dashboard
A1: Emotion Box — Overview
A3: Total bookings | B3: =COUNTA(Clients!A6:A40) -> 0
A4: Confirmed events | B4: =COUNTIF(Clients!L6:L40,"Confirmed")+COUNTIF(Clients!L6:L40,"Deposit Paid")+COUNTIF(Clients!L6:L40,"Completed") -> 0
A5: Completed events | B5: =COUNTIF(Clients!L6:L40,"Completed") -> 0
A6: Total revenue booked (€) | B6: =SUM(Clients!G6:G40) -> 0
A7: Total deposits received (€) | B7: =SUM(Clients!H6:H40) -> 0
A8: Total balance still due (€) | B8: =SUM(Clients!I6:I40) -> 0
A9: Total gift costs (€) | B9: =SUM(Clients!J6:J40) -> 0
A10: Total net profit (€) | B10: =SUM(Clients!K6:K40) -> 0
A11: Silver packages sold | B11: =COUNTIF(Clients!F6:F40,"Silver") -> 0
A12: Gold packages sold | B12: =COUNTIF(Clients!F6:F40,"Gold") -> 0
A13: Royal packages sold | B13: =COUNTIF(Clients!F6:F40,"Royal") -> 0

Sheet Packages & Gifts
A1: Emotion Box — Launch Pricing & Gift Reference
A2: Launch prices (testing phase). Target prices in brackets, to reach once you have 5-10 completed events.
A4: Package | B4: Launch Price (€) | C4: Target Price (€) | D4: Suggested Gift | E4: Gift Cost (€)
A5: Silver | B5: 165 | C5: 290 | D5: Small bouquet or scented candle + card | E5: 18
A6: Gold | B6: 265 | C6: 400 | D6: Fuller bouquet or sparkling wine + chocolates | E6: 35
A7: Royal | B7: 425 | C7: 700 | D7: Champagne + premium bouquet (+ cigars optional) | E7: 75
A9: Tip: buy candles, chocolates, and sparkling wine in bulk at a cash & carry to save time and money. Only buy fresh flowers per event.
